ftb_snbt_lib/__init__.py
ftb_snbt_lib/parse.py
ftb_snbt_lib/parsetab.py
ftb_snbt_lib/tag.py
ftb_snbt_lib/token.py
ftb_snbt_lib/write.py
ftb_snbt_lib/ply/__init__.py
ftb_snbt_lib/ply/cpp.py
ftb_snbt_lib/ply/ctokens.py
ftb_snbt_lib/ply/lex.py
ftb_snbt_lib/ply/yacc.py
ftb_snbt_lib/ply/ygen.py
ftb_snbt_lib-0.4.0.dist-info/LICENSE
ftb_snbt_lib-0.4.0.dist-info/METADATA
ftb_snbt_lib-0.4.0.dist-info/WHEEL
ftb_snbt_lib-0.4.0.dist-info/top_level.txt
ftb_snbt_lib-0.4.0.dist-info/RECORD
