Metadata-Version: 2.1
Name: ftb-snbt-lib
Version: 0.4.0
Summary: A python library to parse, edit, and save FTB snbt tag, which is a variant of the "vanilla" snbt tag.
Author-email: peunsu <peunsu55@gmail.com>
Project-URL: homepage, https://github.com/peunsu/ftb-snbt-lib
Project-URL: repository, https://github.com/peunsu/ftb-snbt-lib
Project-URL: documentation, https://github.com/peunsu/ftb-snbt-lib
Keywords: minecraft,ftb,snbt,parser,library
Classifier: Programming Language :: Python :: 3
Classifier: License :: OSI Approved :: MIT License
Classifier: Operating System :: OS Independent
Requires-Python: >=3.10
License-File: LICENSE
Requires-Dist: wheel
